{
  "repo": "unit4-cte-visit",
  "owner": "vishalsachdev",
  "last_updated": "2026-04-09T14:00:06.623069+00:00",
  "stars": 0,
  "forks": 0,
  "description": "AI in Business \u2014 15-min talk for Unit 4 CTE teachers, March 12 2026",
  "views": {
    "2026-03-06": {
      "count": 0,
      "uniques": 0
    },
    "2026-03-07": {
      "count": 0,
      "uniques": 0
    },
    "2026-03-08": {
      "count": 0,
      "uniques": 0
    },
    "2026-03-09": {
      "count": 0,
      "uniques": 0
    },
    "2026-03-10": {
      "count": 0,
      "uniques": 0
    },
    "2026-03-11": {
      "count": 0,
      "uniques": 0
    },
    "2026-03-12": {
      "count": 0,
      "uniques": 0
    },
    "2026-03-13": {
      "count": 0,
      "uniques": 0
    },
    "2026-03-14": {
      "count": 0,
      "uniques": 0
    },
    "2026-03-15": {
      "count": 0,
      "uniques": 0
    },
    "2026-03-16": {
      "count": 0,
      "uniques": 0
    },
    "2026-03-17": {
      "count": 0,
      "uniques": 0
    },
    "2026-03-18": {
      "count": 0,
      "uniques": 0
    },
    "2026-03-19": {
      "count": 0,
      "uniques": 0
    },
    "2026-03-20": {
      "count": 0,
      "uniques": 0
    },
    "2026-03-21": {
      "count": 0,
      "uniques": 0
    },
    "2026-03-22": {
      "count": 0,
      "uniques": 0
    },
    "2026-03-23": {
      "count": 0,
      "uniques": 0
    },
    "2026-03-24": {
      "count": 0,
      "uniques": 0
    },
    "2026-03-25": {
      "count": 0,
      "uniques": 0
    },
    "2026-03-26": {
      "count": 0,
      "uniques": 0
    },
    "2026-03-27": {
      "count": 0,
      "uniques": 0
    },
    "2026-03-28": {
      "count": 0,
      "uniques": 0
    },
    "2026-03-29": {
      "count": 0,
      "uniques": 0
    },
    "2026-03-30": {
      "count": 2,
      "uniques": 1
    },
    "2026-03-31": {
      "count": 0,
      "uniques": 0
    },
    "2026-04-01": {
      "count": 0,
      "uniques": 0
    },
    "2026-04-02": {
      "count": 0,
      "uniques": 0
    },
    "2026-04-03": {
      "count": 0,
      "uniques": 0
    },
    "2026-04-04": {
      "count": 0,
      "uniques": 0
    },
    "2026-04-05": {
      "count": 0,
      "uniques": 0
    },
    "2026-04-06": {
      "count": 0,
      "uniques": 0
    },
    "2026-04-07": {
      "count": 0,
      "uniques": 0
    },
    "2026-04-08": {
      "count": 0,
      "uniques": 0
    }
  },
  "clones": {
    "2026-03-06": {
      "count": 0,
      "uniques": 0
    },
    "2026-03-07": {
      "count": 0,
      "uniques": 0
    },
    "2026-03-08": {
      "count": 0,
      "uniques": 0
    },
    "2026-03-09": {
      "count": 0,
      "uniques": 0
    },
    "2026-03-10": {
      "count": 0,
      "uniques": 0
    },
    "2026-03-11": {
      "count": 0,
      "uniques": 0
    },
    "2026-03-12": {
      "count": 15,
      "uniques": 14
    },
    "2026-03-13": {
      "count": 2,
      "uniques": 2
    },
    "2026-03-14": {
      "count": 0,
      "uniques": 0
    },
    "2026-03-15": {
      "count": 2,
      "uniques": 2
    },
    "2026-03-16": {
      "count": 0,
      "uniques": 0
    },
    "2026-03-17": {
      "count": 0,
      "uniques": 0
    },
    "2026-03-18": {
      "count": 0,
      "uniques": 0
    },
    "2026-03-19": {
      "count": 2,
      "uniques": 2
    },
    "2026-03-20": {
      "count": 0,
      "uniques": 0
    },
    "2026-03-21": {
      "count": 1,
      "uniques": 1
    },
    "2026-03-22": {
      "count": 2,
      "uniques": 2
    },
    "2026-03-23": {
      "count": 1,
      "uniques": 1
    },
    "2026-03-24": {
      "count": 1,
      "uniques": 1
    },
    "2026-03-25": {
      "count": 0,
      "uniques": 0
    },
    "2026-03-26": {
      "count": 0,
      "uniques": 0
    },
    "2026-03-27": {
      "count": 1,
      "uniques": 1
    },
    "2026-03-28": {
      "count": 0,
      "uniques": 0
    },
    "2026-03-29": {
      "count": 2,
      "uniques": 2
    },
    "2026-03-30": {
      "count": 0,
      "uniques": 0
    },
    "2026-03-31": {
      "count": 0,
      "uniques": 0
    },
    "2026-04-01": {
      "count": 0,
      "uniques": 0
    },
    "2026-04-02": {
      "count": 0,
      "uniques": 0
    },
    "2026-04-03": {
      "count": 0,
      "uniques": 0
    },
    "2026-04-04": {
      "count": 1,
      "uniques": 1
    },
    "2026-04-05": {
      "count": 0,
      "uniques": 0
    },
    "2026-04-06": {
      "count": 1,
      "uniques": 1
    },
    "2026-04-07": {
      "count": 1,
      "uniques": 1
    },
    "2026-04-08": {
      "count": 1,
      "uniques": 1
    }
  },
  "referrers": [
    {
      "referrer": "github.com",
      "count": 2,
      "uniques": 1
    }
  ],
  "paths": [
    {
      "path": "/vishalsachdev/unit4-cte-visit",
      "title": "Overview",
      "count": 2,
      "uniques": 1
    }
  ]
}
